duro_tools/__init__.py
duro_tools/acq_results.py
duro_tools/action_logger.py
duro_tools/almanac.py
duro_tools/bootload_v3.py
duro_tools/diagnostics.py
duro_tools/fileio.py
duro_tools/heartbeat.py
duro_tools/interpolate_event_positions.py
duro_tools/sbp_msg_2_csv.py
duro_tools/sbpjson_expand.py
duro_tools/serial_link.py
duro_tools/settings.py
duro_tools/simulator_almanac_generator.py
duro_tools/timeout.py
duro_tools/utils.py
duro_tools-2.0.0.dev1.dist-info/METADATA
duro_tools-2.0.0.dev1.dist-info/WHEEL
duro_tools-2.0.0.dev1.dist-info/RECORD
