Metadata-Version: 2.1
Name: duro-tools
Version: 2.0.0.dev1
Summary: 
Author: Nathaniel Mallick
Author-email: nmallick@carnegierobotics.com
Requires-Python: >=3.10,<4.0
Classifier: Programming Language :: Python :: 3
Classifier: Programming Language :: Python :: 3.10
Classifier: Programming Language :: Python :: 3.11
Classifier: Programming Language :: Python :: 3.12
Requires-Dist: future (>=1.0.0,<2.0.0)
Requires-Dist: monotonic (>=1.6,<2.0)
Requires-Dist: numpy (==2.2.0)
Requires-Dist: pyyaml (>=6.0.2,<7.0.0)
Requires-Dist: sbp (==4.1.1)
